brasil.gov.paginadestaque-1.0b1-py2.7-nspkg.pth
brasil.gov.paginadestaque-1.0b1.dist-info/top_level.txt
brasil.gov.paginadestaque-1.0b1.dist-info/WHEEL
brasil.gov.paginadestaque-1.0b1.dist-info/entry_points.txt
brasil.gov.paginadestaque-1.0b1.dist-info/metadata.json
brasil.gov.paginadestaque-1.0b1.dist-info/DESCRIPTION.rst
brasil.gov.paginadestaque-1.0b1.dist-info/METADATA
brasil.gov.paginadestaque-1.0b1.dist-info/namespace_packages.txt
brasil.gov.paginadestaque-1.0b1.dist-info/RECORD
brasil/gov/paginadestaque/testing.py
brasil/gov/paginadestaque/interfaces.py
brasil/gov/paginadestaque/profiles.zcml
brasil/gov/paginadestaque/config.py
brasil/gov/paginadestaque/configure.zcml
brasil/gov/paginadestaque/__init__.py
brasil/gov/paginadestaque/themes.zcml
brasil/gov/paginadestaque/behaviors/interfaces.py
brasil/gov/paginadestaque/behaviors/configure.zcml
brasil/gov/paginadestaque/behaviors/__init__.py
brasil/gov/paginadestaque/behaviors/expiration.py
brasil/gov/paginadestaque/behaviors/metadata.py
brasil/gov/paginadestaque/locales/brasil.gov.paginadestaque.pot
brasil/gov/paginadestaque/locales/plone.pot
brasil/gov/paginadestaque/locales/manual.pot
brasil/gov/paginadestaque/locales/pt_BR/LC_MESSAGES/plone.po
brasil/gov/paginadestaque/locales/pt_BR/LC_MESSAGES/brasil.gov.paginadestaque.po
brasil/gov/paginadestaque/themes/destaques-cinza/style.css
brasil/gov/paginadestaque/themes/destaques-cinza/index.html
brasil/gov/paginadestaque/themes/destaques-cinza/style.less
brasil/gov/paginadestaque/themes/destaques-cinza/preview.png
brasil/gov/paginadestaque/themes/destaques-cinza/rules.xml
brasil/gov/paginadestaque/themes/destaques-cinza/manifest.cfg
brasil/gov/paginadestaque/themes/destaques-cinza/img/header.gif
brasil/gov/paginadestaque/themes/destaques-cinza/img/bullet.png
brasil/gov/paginadestaque/themes/destaques-cinza/img/sprite-setas.png
brasil/gov/paginadestaque/themes/destaques-cinza/img/readmoredarkgray.png
brasil/gov/paginadestaque/themes/destaques-cinza/img/shadow-bottom.gif
brasil/gov/paginadestaque/themes/destaques-cinza/img/icone-related-items.png
brasil/gov/paginadestaque/themes/destaques-cinza/img/favicon.ico
brasil/gov/paginadestaque/themes/destaques-cinza/img/bg-menu-mobile.png
brasil/gov/paginadestaque/themes/destaques-cinza/img/em-destaque.png
brasil/gov/paginadestaque/themes/destaques-cinza/img/readmorepurple.png
