Metadata-Version: 2.0
Name: brasil.gov.paginadestaque
Version: 1.0b1
Summary: Complemento ao Portal Padrao para criacao de microsites e campanhas
Home-page: https://github.com/plonegovbr/brasil.gov.paginadestaque
Author: PloneGov.Br
Author-email: gov@plone.org.br
License: UNKNOWN
Keywords: plone microsite destaque brasil egov
Platform: UNKNOWN
Classifier: Development Status :: 4 - Beta
Classifier: Environment :: Web Environment
Classifier: Framework :: Plone
Classifier: Framework :: Plone :: 4.3
Classifier: Intended Audience :: System Administrators
Classifier: License :: OSI Approved :: GNU General Public License v2 (GPLv2)
Classifier: Operating System :: OS Independent
Classifier: Programming Language :: Python
Classifier: Programming Language :: Python :: 2.7
Classifier: Topic :: Software Development :: Libraries :: Python Modules
Requires-Dist: collective.cover
Requires-Dist: collective.z3cform.datagridfield
Requires-Dist: five.grok
Requires-Dist: plone.api
Requires-Dist: plone.app.upgrade
Requires-Dist: Products.CMFPlone (>=4.3)
Requires-Dist: Products.GenericSetup
Requires-Dist: sc.microsite (>=1.0b4)
Requires-Dist: setuptools
Requires-Dist: zope.i18nmessageid
Requires-Dist: zope.interface
Provides-Extra: test
Requires-Dist: mock; extra == 'test'
Requires-Dist: plone.app.robotframework; extra == 'test'
Requires-Dist: plone.app.testing[robot] (>=4.2.2); extra == 'test'
Requires-Dist: plone.browserlayer; extra == 'test'
Requires-Dist: plone.testing; extra == 'test'
Requires-Dist: robotsuite; extra == 'test'
